phylax/__init__.py
phylax/_internal/__init__.py
phylax/_internal/capture.py
phylax/_internal/context.py
phylax/_internal/decorator.py
phylax/_internal/graph.py
phylax/_internal/schema.py
phylax/_internal/adapters/__init__.py
phylax/_internal/adapters/gemini.py
phylax/_internal/adapters/llama.py
phylax/_internal/adapters/openai.py
phylax/_internal/expectations/__init__.py
phylax/_internal/expectations/evaluator.py
phylax/_internal/expectations/rules.py
phylax/assets/logo/phylax_favicon.png
phylax/assets/logo/phylax_logo.png
phylax/cli/__init__.py
phylax/cli/main.py
phylax/server/__init__.py
phylax/server/main.py
phylax/server/routes/__init__.py
phylax/server/routes/chat.py
phylax/server/routes/replay.py
phylax/server/routes/traces.py
phylax/server/storage/__init__.py
phylax/server/storage/files.py
phylax/server/storage/sqlite.py
phylax/ui/app.js
phylax/ui/index.html
phylax-1.0.3.dist-info/licenses/LICENSE
phylax-1.0.3.dist-info/METADATA
phylax-1.0.3.dist-info/WHEEL
phylax-1.0.3.dist-info/entry_points.txt
phylax-1.0.3.dist-info/top_level.txt
phylax-1.0.3.dist-info/RECORD
