Metadata-Version: 2.4
Name: phylax
Version: 1.0.3
Summary: Deterministic regression enforcement for LLM systems.
Author: Phylax Team
License: MIT
Project-URL: Homepage, https://github.com/xXMohitXx/Phylax
Project-URL: Documentation, https://github.com/xXMohitXx/Phylax#readme
Project-URL: Repository, https://github.com/xXMohitXx/Phylax
Keywords: llm,testing,regression,ci,deterministic,tracing
Classifier: Development Status :: 5 - Production/Stable
Classifier: Intended Audience :: Developers
Classifier: License :: OSI Approved :: MIT License
Classifier: Programming Language :: Python :: 3
Classifier: Programming Language :: Python :: 3.10
Classifier: Programming Language :: Python :: 3.11
Classifier: Programming Language :: Python :: 3.12
Classifier: Topic :: Software Development :: Testing
Classifier: Topic :: Software Development :: Quality Assurance
Requires-Python: >=3.10
License-File: LICENSE
Requires-Dist: pydantic>=2.5.0
Requires-Dist: pyyaml>=6.0
Provides-Extra: server
Requires-Dist: fastapi>=0.109.0; extra == "server"
Requires-Dist: uvicorn[standard]>=0.27.0; extra == "server"
Provides-Extra: openai
Requires-Dist: openai>=1.0.0; extra == "openai"
Provides-Extra: google
Requires-Dist: google-generativeai>=0.8.0; extra == "google"
Provides-Extra: dev
Requires-Dist: pytest>=7.0.0; extra == "dev"
Requires-Dist: pytest-asyncio>=0.21.0; extra == "dev"
Requires-Dist: httpx>=0.26.0; extra == "dev"
Requires-Dist: requests>=2.31.0; extra == "dev"
Provides-Extra: all
Requires-Dist: phylax[google,openai,server]; extra == "all"
Dynamic: license-file
